{
  "main": {
    "id": "75a35037e3a43bb4",
    "type": "split",
    "children": [
      {
        "id": "4c9eb86ad3ae08db",
        "type": "tabs",
        "children": [
          {
            "id": "2136d28f0da32ba9",
            "type": "leaf",
            "state": {
              "type": "markdown",
              "state": {
                "file": "laravel/laravel_flush_error.md",
                "mode": "source",
                "backlinks": true,
                "source": false
              }
            }
          },
          {
            "id": "446dfe2ad797ddbd",
            "type": "leaf",
            "state": {
              "type": "markdown",
              "state": {
                "file": "laravel/laravel_namespace.md",
                "mode": "source",
                "backlinks": true,
                "source": false
              }
            }
          },
          {
            "id": "4e7122aa8e294a5c",
            "type": "leaf",
            "state": {
              "type": "markdown",
              "state": {
                "file": "laravel/laravel_flush_error.md",
                "mode": "source",
                "backlinks": true,
                "source": false
              }
            }
          },
          {
            "id": "892120ae20bf851a",
            "type": "leaf",
            "state": {
              "type": "markdown",
              "state": {
                "file": "wp/WordPress カスタム投稿.md",
                "mode": "source",
                "backlinks": true,
                "source": false
              }
            }
          }
        ],
        "currentTab": 3
      }
    ],
    "direction": "vertical"
  },
  "left": {
    "id": "745783d6725a8a9b",
    "type": "split",
    "children": [
      {
        "id": "d445588b32320ff6",
        "type": "tabs",
        "children": [
          {
            "id": "bd1d67f257f06a19",
            "type": "leaf",
            "state": {
              "type": "file-explorer",
              "state": {
                "sortOrder": "alphabetical"
              }
            }
          },
          {
            "id": "deb8fe82d8232d6e",
            "type": "leaf",
            "state": {
              "type": "search",
              "state": {
                "query": "journal",
                "matchingCase": false,
                "explainSearch": false,
                "collapseAll": false,
                "extraContext": false,
                "sortOrder": "alphabetical"
              }
            }
          },
          {
            "id": "a7738e972d795bd0",
            "type": "leaf",
            "state": {
              "type": "starred",
              "state": {}
            }
          }
        ]
      }
    ],
    "direction": "horizontal",
    "width": 300
  },
  "right": {
    "id": "5f89aa6edebf78a7",
    "type": "split",
    "children": [
      {
        "id": "ab7c5c04f2655d91",
        "type": "tabs",
        "children": [
          {
            "id": "98ea72e6970c6da7",
            "type": "leaf",
            "state": {
              "type": "backlink",
              "state": {
                "file": "wp/WordPress カスタム投稿.md",
                "collapseAll": false,
                "extraContext": false,
                "sortOrder": "alphabetical",
                "showSearch": false,
                "searchQuery": "",
                "backlinkCollapsed": false,
                "unlinkedCollapsed": true
              }
            }
          },
          {
            "id": "954ae8d796d5c477",
            "type": "leaf",
            "state": {
              "type": "outgoing-link",
              "state": {
                "file": "wp/WordPress カスタム投稿.md",
                "linksCollapsed": false,
                "unlinkedCollapsed": true
              }
            }
          },
          {
            "id": "47837a40befe4900",
            "type": "leaf",
            "state": {
              "type": "tag",
              "state": {
                "sortOrder": "frequency",
                "useHierarchy": true
              }
            }
          },
          {
            "id": "5269a7c465c55cdb",
            "type": "leaf",
            "state": {
              "type": "outline",
              "state": {
                "file": "wp/WordPress カスタム投稿.md"
              }
            }
          },
          {
            "id": "c03d74501afde445",
            "type": "leaf",
            "state": {
              "type": "advanced-tables-toolbar",
              "state": {}
            }
          }
        ],
        "currentTab": 3
      }
    ],
    "direction": "horizontal",
    "width": 300,
    "collapsed": true
  },
  "left-ribbon": {
    "hiddenItems": {
      "switcher:クイックスイッチャーを開く": false,
      "graph:グラフビューを開く": false,
      "canvas:新規キャンバスを作成": false,
      "daily-notes:今日のデイリーノートを開く": false,
      "templates:テンプレートを挿入": false,
      "command-palette:コマンドパレットを開く": false,
      "table-editor-obsidian:Advanced Tables Toolbar": false
    }
  },
  "active": "892120ae20bf851a",
  "lastOpenFiles": [
    "laravel/laravel_flush_error.md",
    "wp/WordPress カスタム投稿.md",
    "laravel/laravel_validate.md",
    "laravel/laravel_s3.md",
    "laravel/laravel_namespace.md",
    "laravel/laravel_auth.md",
    "laravel/laravel_file.md",
    "laravel_csv.md",
    "laravel/laravel-vue.md",
    "laravel/laravel_asset_url.md",
    "laravel/laravel_carbon.md",
    "nodenv.md",
    "cdn.md",
    "js/axios.md",
    "ecr_ecs.md",
    "git/gitignore.md",
    "openssl.md",
    "linux.md",
    "m1mac.md",
    "mysqldump.md",
    "sort.md",
    "shortcut.md",
    "laravel/laravel_facade.md",
    "linq.md",
    "jq.md",
    "index2.md",
    "api"
  ]
}